{
    "US": "United States",
    "CN": "China",
    "IN": "India",
    "JP": "Japan",
    "DE": "Germany",
    "GB": "United Kingdom",
    "FR": "France",
    "BR": "Brazil",
    "CA": "Canada",
    "AU": "Australia",
    "RU": "Russia",
    "IT": "Italy",
    "ES": "Spain",
    "SE": "Sweden",
    "NL": "Netherlands",
    "CH": "Switzerland",
    "PL": "Poland",
    "BE": "Belgium",
    "AT": "Austria",
    "DK": "Denmark",
    "FI": "Finland",
    "NO": "Norway",
    "IE": "Ireland",
    "PT": "Portugal",
    "GR": "Greece",
    "CZ": "Czech Republic",
    "HU": "Hungary",
    "SK": "Slovakia",
    "RO": "Romania",
    "BG": "Bulgaria",
    "TR": "Turkey",
    "SA": "Saudi Arabia",
    "AR": "Argentina",
    "MX": "Mexico",
    "KR": "South Korea",
    "ID": "Indonesia",
    "VN": "Vietnam"
}
